{"nm":"Main Scene","ddd":0,"h":512,"w":512,"meta":{"g":"@lottiefiles/creator 1.71.0"},"layers":[{"ty":0,"nm":"door_open_24dp_E3E3E3_FILL0_wght400_GRAD0_opsz24","sr":1,"st":0,"op":150,"ip":0,"hd":false,"ddd":0,"bm":0,"hasMask":false,"ao":0,"ks":{"a":{"a":0,"k":[12,12]},"s":{"a":1,"k":[{"o":{"x":0.167,"y":0.167},"i":{"x":0.833,"y":0.833},"s":[95,95],"t":1},{"s":[1461.6666666666667,1453.3333333333333],"t":45}]},"sk":{"a":0,"k":0},"p":{"a":0,"k":[256,256]},"r":{"a":0,"k":0},"sa":{"a":0,"k":0},"o":{"a":1,"k":[{"o":{"x":0.167,"y":0.167},"i":{"x":0.833,"y":0.833},"s":[0],"t":1},{"s":[100],"t":45}]}},"w":24,"h":24,"refId":"precomp_Shape Layer - SVG_L4OABuwvcp_f5659d1e-0d9d-43be-b558-c3b377436fb7","ind":1}],"v":"5.7.0","fr":30,"op":150,"ip":0,"assets":[{"nm":"door_open_24dp_E3E3E3_FILL0_wght400_GRAD0_opsz24","id":"precomp_Shape Layer - SVG_oSpUBwu6ty_19f4670a-21e7-4309-9587-e0cd1d19a69a","fr":30,"layers":[{"ty":4,"nm":"Shape Layer 1","sr":1,"st":0,"op":150,"ip":0,"hd":false,"ddd":0,"bm":0,"hasMask":false,"ao":0,"ks":{"a":{"a":0,"k":[480,-480]},"s":{"a":0,"k":[2.5,2.5]},"sk":{"a":0,"k":0},"p":{"a":0,"k":[12,12]},"r":{"a":0,"k":0},"sa":{"a":0,"k":0},"o":{"a":0,"k":100}},"shapes":[{"ty":"gr","bm":0,"hd":false,"nm":"Group 1","np":5,"it":[{"ty":"sh","bm":0,"hd":false,"nm":"Path 1","d":1,"ks":{"a":0,"k":{"c":true,"i":[[0,0],[-7.67,7.67],[0,11.33],[7.67,7.67],[11.33,0],[7.67,-7.67],[0,-11.33],[-7.67,-7.67],[-11.33,0]],"o":[[11.33,0],[7.67,-7.67],[0,-11.33],[-7.67,-7.67],[-11.33,0],[-7.67,7.67],[0,11.33],[7.67,7.67],[0,0]],"v":[[440,-440],[468.5,-451.5],[480,-480],[468.5,-508.5],[440,-520],[411.5,-508.5],[400,-480],[411.5,-451.5],[440,-440]]}}},{"ty":"sh","bm":0,"hd":false,"nm":"Path 2","d":1,"ks":{"a":0,"k":{"c":true,"i":[[0,0],[0,0],[0,0],[0,0],[6,8],[9.33,1.33],[0,0],[0,0],[0,0],[-18.67,-22],[0,-29.33],[0,0],[0,0]],"o":[[0,0],[0,0],[0,0],[0,-10],[-6,-8],[0,0],[0,0],[0,0],[29.33,5.33],[18.67,22],[0,0],[0,0],[0,0]],"v":[[280,-120],[280,-200],[520,-240],[520,-685],[511,-712],[488,-726],[280,-760],[280,-840],[500,-804],[572,-763],[600,-686],[600,-174],[280,-120]]}}},{"ty":"sh","bm":0,"hd":false,"nm":"Path 3","d":1,"ks":{"a":0,"k":{"c":true,"i":[[0,0],[0,0],[0,0],[0,0],[-15.67,15.33],[-22,0],[0,0],[-15.33,-15.33],[0,-22.67],[0,0],[0,0],[0,0],[0,0]],"o":[[0,0],[0,0],[0,0],[0,-22.67],[15.67,-15.33],[0,0],[22.67,0],[15.33,15.33],[0,0],[0,0],[0,0],[0,0],[0,0]],"v":[[120,-120],[120,-200],[200,-200],[200,-760],[223.5,-817],[280,-840],[680,-840],[737,-817],[760,-760],[760,-200],[840,-200],[840,-120],[120,-120]]}}},{"ty":"sh","bm":0,"hd":false,"nm":"Path 4","d":1,"ks":{"a":0,"k":{"c":true,"i":[[0,0],[0,0],[0,0],[0,0],[0,0]],"o":[[0,0],[0,0],[0,0],[0,0],[0,0]],"v":[[280,-200],[680,-200],[680,-760],[280,-760],[280,-200]]}}},{"ty":"fl","bm":0,"hd":false,"nm":"Fill","c":{"a":0,"k":[0,0.8667,0.702,1]},"r":1,"o":{"a":0,"k":100}},{"ty":"tr","a":{"a":0,"k":[480,-480]},"s":{"a":0,"k":[100,100]},"sk":{"a":0,"k":0},"p":{"a":0,"k":[480,-480]},"r":{"a":0,"k":0},"sa":{"a":0,"k":0},"o":{"a":0,"k":100}}]}],"ind":1}]},{"nm":"door_open_24dp_E3E3E3_FILL0_wght400_GRAD0_opsz24_1","id":"precomp_Shape Layer - SVG_L4OABuwvcp_f5659d1e-0d9d-43be-b558-c3b377436fb7","fr":30,"layers":[{"ty":0,"nm":"door_open_24dp_E3E3E3_FILL0_wght400_GRAD0_opsz24","sr":1,"st":0,"op":150,"ip":0,"hd":false,"ddd":0,"bm":0,"hasMask":false,"ao":0,"ks":{"a":{"a":0,"k":[12,12]},"s":{"a":0,"k":[100,100]},"sk":{"a":0,"k":0},"p":{"a":0,"k":[12,12]},"r":{"a":0,"k":0},"sa":{"a":0,"k":0},"o":{"a":0,"k":100}},"w":24,"h":24,"refId":"precomp_Shape Layer - SVG_vxSPB0ypRm_c2548470-3d45-4e94-b99a-85fac0e8f6b6","ind":1}]},{"nm":"door_open_24dp_E3E3E3_FILL0_wght400_GRAD0_opsz24_2","id":"precomp_Shape Layer - SVG_vxSPB0ypRm_c2548470-3d45-4e94-b99a-85fac0e8f6b6","fr":30,"layers":[{"ty":4,"nm":"Shape Layer 1","sr":1,"st":0,"op":150,"ip":0,"hd":false,"ddd":0,"bm":0,"hasMask":false,"ao":0,"ks":{"a":{"a":0,"k":[480,-480]},"s":{"a":0,"k":[2.5,2.5]},"sk":{"a":0,"k":0},"p":{"a":0,"k":[12,12]},"r":{"a":0,"k":0},"sa":{"a":0,"k":0},"o":{"a":0,"k":100}},"shapes":[{"ty":"gr","bm":0,"hd":false,"nm":"Group 1","np":5,"it":[{"ty":"sh","bm":0,"hd":false,"nm":"Path 1","d":1,"ks":{"a":0,"k":{"c":true,"i":[[0,0],[-7.67,7.67],[0,11.33],[7.67,7.67],[11.33,0],[7.67,-7.67],[0,-11.33],[-7.67,-7.67],[-11.33,0]],"o":[[11.33,0],[7.67,-7.67],[0,-11.33],[-7.67,-7.67],[-11.33,0],[-7.67,7.67],[0,11.33],[7.67,7.67],[0,0]],"v":[[440,-440],[468.5,-451.5],[480,-480],[468.5,-508.5],[440,-520],[411.5,-508.5],[400,-480],[411.5,-451.5],[440,-440]]}}},{"ty":"sh","bm":0,"hd":false,"nm":"Path 2","d":1,"ks":{"a":0,"k":{"c":true,"i":[[0,0],[0,0],[0,0],[0,0],[6,8],[9.33,1.33],[0,0],[0,0],[0,0],[-18.67,-22],[0,-29.33],[0,0],[0,0]],"o":[[0,0],[0,0],[0,0],[0,-10],[-6,-8],[0,0],[0,0],[0,0],[29.33,5.33],[18.67,22],[0,0],[0,0],[0,0]],"v":[[280,-120],[280,-200],[520,-240],[520,-685],[511,-712],[488,-726],[280,-760],[280,-840],[500,-804],[572,-763],[600,-686],[600,-174],[280,-120]]}}},{"ty":"sh","bm":0,"hd":false,"nm":"Path 3","d":1,"ks":{"a":0,"k":{"c":true,"i":[[0,0],[0,0],[0,0],[0,0],[-15.67,15.33],[-22,0],[0,0],[-15.33,-15.33],[0,-22.67],[0,0],[0,0],[0,0],[0,0]],"o":[[0,0],[0,0],[0,0],[0,-22.67],[15.67,-15.33],[0,0],[22.67,0],[15.33,15.33],[0,0],[0,0],[0,0],[0,0],[0,0]],"v":[[120,-120],[120,-200],[200,-200],[200,-760],[223.5,-817],[280,-840],[680,-840],[737,-817],[760,-760],[760,-200],[840,-200],[840,-120],[120,-120]]}}},{"ty":"sh","bm":0,"hd":false,"nm":"Path 4","d":1,"ks":{"a":0,"k":{"c":true,"i":[[0,0],[0,0],[0,0],[0,0],[0,0]],"o":[[0,0],[0,0],[0,0],[0,0],[0,0]],"v":[[280,-200],[680,-200],[680,-760],[280,-760],[280,-200]]}}},{"ty":"fl","bm":0,"hd":false,"nm":"Fill","c":{"a":0,"k":[0,0.8667,0.702,1]},"r":1,"o":{"a":0,"k":100}},{"ty":"tr","a":{"a":0,"k":[480,-480]},"s":{"a":0,"k":[100,100]},"sk":{"a":0,"k":0},"p":{"a":0,"k":[480,-480]},"r":{"a":0,"k":0},"sa":{"a":0,"k":0},"o":{"a":0,"k":100}}]}],"ind":1}]}]}